{"route_id":"jul-aep-gyn","label":"Buenos Aires (Aeroparque) - Goiânia","origin":"AEP","destination":"GYN","tripType":"oneway","stayNights":null,"updated_at":"2026-07-20T10:55:49.817Z","options":[{"depart":"2026-07-30","return":null,"current":{"gol":{"price":1761,"currency":"BRL","scraped_at":"2026-07-20T10:50:37.015Z","link":"https://b2c.voegol.com.br/compra/busca-parceiros?pv=br&tipo=DF&lang=pt-BR&de=AEP&para=GYN&ida=30-07-2026&ADT=1&ADL=0&CHD=0&INF=0&voebiz=0","is_historical_min":false,"airline":null}},"best":{"site":"gol","price":1761,"currency":"BRL"},"history":{"gol":{"currency":"BRL","min":1746,"avg":1801,"points":[["2026-07-12",1758],["2026-07-13",1758],["2026-07-14",1761],["2026-07-15",1746],["2026-07-16",1746],["2026-07-17",1754],["2026-07-18",1761],["2026-07-19",1761],["2026-07-20",1761]]}}},{"depart":"2026-07-31","return":null,"current":{"gol":{"price":1761,"currency":"BRL","scraped_at":"2026-07-20T10:50:37.015Z","link":"https://b2c.voegol.com.br/compra/busca-parceiros?pv=br&tipo=DF&lang=pt-BR&de=AEP&para=GYN&ida=31-07-2026&ADT=1&ADL=0&CHD=0&INF=0&voebiz=0","is_historical_min":false,"airline":null}},"best":{"site":"gol","price":1761,"currency":"BRL"},"history":{"gol":{"currency":"BRL","min":1523,"avg":1715,"points":[["2026-07-12",1523],["2026-07-13",1523],["2026-07-14",1761],["2026-07-15",1746],["2026-07-16",1746],["2026-07-17",1754],["2026-07-18",1761],["2026-07-19",1761],["2026-07-20",1761]]}}},{"depart":"2026-08-01","return":null,"current":{"gol":{"price":1947,"currency":"BRL","scraped_at":"2026-07-20T10:50:37.015Z","link":"https://b2c.voegol.com.br/compra/busca-parceiros?pv=br&tipo=DF&lang=pt-BR&de=AEP&para=GYN&ida=01-08-2026&ADT=1&ADL=0&CHD=0&INF=0&voebiz=0","is_historical_min":false,"airline":null}},"best":{"site":"gol","price":1947,"currency":"BRL"},"history":{"gol":{"currency":"BRL","min":1523,"avg":1737,"points":[["2026-07-12",1523],["2026-07-13",1523],["2026-07-14",1526],["2026-07-15",1746],["2026-07-16",1746],["2026-07-17",1754],["2026-07-18",1947],["2026-07-19",1947],["2026-07-20",1947]]}}},{"depart":"2026-08-02","return":null,"current":{"gol":{"price":1763,"currency":"BRL","scraped_at":"2026-07-20T10:50:37.015Z","link":"https://b2c.voegol.com.br/compra/busca-parceiros?pv=br&tipo=DF&lang=pt-BR&de=AEP&para=GYN&ida=02-08-2026&ADT=1&ADL=0&CHD=0&INF=0&voebiz=0","is_historical_min":false,"airline":null}},"best":{"site":"gol","price":1763,"currency":"BRL"},"history":{"gol":{"currency":"BRL","min":1523,"avg":1726,"points":[["2026-07-12",1523],["2026-07-13",1616],["2026-07-14",1619],["2026-07-15",1746],["2026-07-16",1746],["2026-07-17",1754],["2026-07-18",1763],["2026-07-19",1763],["2026-07-20",1763]]}}},{"depart":"2026-08-03","return":null,"current":{"gol":{"price":1761,"currency":"BRL","scraped_at":"2026-07-20T10:50:37.015Z","link":"https://b2c.voegol.com.br/compra/busca-parceiros?pv=br&tipo=DF&lang=pt-BR&de=AEP&para=GYN&ida=03-08-2026&ADT=1&ADL=0&CHD=0&INF=0&voebiz=0","is_historical_min":false,"airline":null}},"best":{"site":"gol","price":1761,"currency":"BRL"},"history":{"gol":{"currency":"BRL","min":1523,"avg":1708,"points":[["2026-07-12",1523],["2026-07-13",1523],["2026-07-14",1619],["2026-07-15",1745],["2026-07-16",1745],["2026-07-17",1753],["2026-07-18",1781],["2026-07-19",1761],["2026-07-20",1761]]}}},{"depart":"2026-08-04","return":null,"current":{"gol":{"price":1471,"currency":"BRL","scraped_at":"2026-07-20T10:50:37.015Z","link":"https://b2c.voegol.com.br/compra/busca-parceiros?pv=br&tipo=DF&lang=pt-BR&de=AEP&para=GYN&ida=04-08-2026&ADT=1&ADL=0&CHD=0&INF=0&voebiz=0","is_historical_min":false,"airline":null}},"best":{"site":"gol","price":1471,"currency":"BRL"},"history":{"gol":{"currency":"BRL","min":1151,"avg":1392,"points":[["2026-07-12",1151],["2026-07-13",1151],["2026-07-14",1471],["2026-07-15",1458],["2026-07-16",1458],["2026-07-17",1465],["2026-07-18",1471],["2026-07-19",1471],["2026-07-20",1471]]}}},{"depart":"2026-08-05","return":null,"current":{"gol":{"price":1471,"currency":"BRL","scraped_at":"2026-07-20T10:50:37.015Z","link":"https://b2c.voegol.com.br/compra/busca-parceiros?pv=br&tipo=DF&lang=pt-BR&de=AEP&para=GYN&ida=05-08-2026&ADT=1&ADL=0&CHD=0&INF=0&voebiz=0","is_historical_min":false,"airline":null}},"best":{"site":"gol","price":1471,"currency":"BRL"},"history":{"gol":{"currency":"BRL","min":1151,"avg":1392,"points":[["2026-07-12",1151],["2026-07-13",1151],["2026-07-14",1471],["2026-07-15",1458],["2026-07-16",1458],["2026-07-17",1465],["2026-07-18",1471],["2026-07-19",1471],["2026-07-20",1471]]}}},{"depart":"2026-08-06","return":null,"current":{"gol":{"price":1679,"currency":"BRL","scraped_at":"2026-07-20T10:50:37.015Z","link":"https://b2c.voegol.com.br/compra/busca-parceiros?pv=br&tipo=DF&lang=pt-BR&de=AEP&para=GYN&ida=06-08-2026&ADT=1&ADL=0&CHD=0&INF=0&voebiz=0","is_historical_min":false,"airline":null}},"best":{"site":"gol","price":1679,"currency":"BRL"},"history":{"gol":{"currency":"BRL","min":1151,"avg":1503,"points":[["2026-07-12",1151],["2026-07-13",1151],["2026-07-14",1471],["2026-07-15",1605],["2026-07-16",1605],["2026-07-17",1612],["2026-07-18",1618],["2026-07-19",1618],["2026-07-20",1679]]}}},{"depart":"2026-08-07","return":null,"current":{"gol":{"price":1760,"currency":"BRL","scraped_at":"2026-07-20T10:50:37.015Z","link":"https://b2c.voegol.com.br/compra/busca-parceiros?pv=br&tipo=DF&lang=pt-BR&de=AEP&para=GYN&ida=07-08-2026&ADT=1&ADL=0&CHD=0&INF=0&voebiz=0","is_historical_min":false,"airline":null}},"best":{"site":"gol","price":1760,"currency":"BRL"},"history":{"gol":{"currency":"BRL","min":1151,"avg":1591,"points":[["2026-07-12",1151],["2026-07-13",1151],["2026-07-14",1471],["2026-07-15",1745],["2026-07-16",1745],["2026-07-17",1753],["2026-07-18",1760],["2026-07-19",1760],["2026-07-20",1760]]}}},{"depart":"2026-08-08","return":null,"current":{"gol":{"price":1679,"currency":"BRL","scraped_at":"2026-07-20T10:50:37.015Z","link":"https://b2c.voegol.com.br/compra/busca-parceiros?pv=br&tipo=DF&lang=pt-BR&de=AEP&para=GYN&ida=08-08-2026&ADT=1&ADL=0&CHD=0&INF=0&voebiz=0","is_historical_min":false,"airline":null}},"best":{"site":"gol","price":1679,"currency":"BRL"},"history":{"gol":{"currency":"BRL","min":1151,"avg":1540,"points":[["2026-07-12",1151],["2026-07-13",1151],["2026-07-14",1471],["2026-07-15",1665],["2026-07-16",1664],["2026-07-17",1672],["2026-07-18",1679],["2026-07-19",1679],["2026-07-20",1679]]}}}]}